propertiesio/__init__.py
propertiesio/propertiesIO.py
properties_chenxi12-0.0.1.dist-info/LICENSE.txt
properties_chenxi12-0.0.1.dist-info/METADATA
properties_chenxi12-0.0.1.dist-info/WHEEL
properties_chenxi12-0.0.1.dist-info/top_level.txt
properties_chenxi12-0.0.1.dist-info/RECORD
