Metadata-Version: 2.2
Name: properties-chenxi12
Version: 0.0.1
Summary: properties
Home-page: https://github.com/zhangjiahuichenxi/propertiesio
Author: chenxi
Author-email: chenxi201412@outlook.com
Classifier: Programming Language :: Python :: 3
Classifier: License :: OSI Approved :: BSD License
Classifier: Operating System :: OS Independent
Requires-Python: >=3.6
License-File: LICENSE.txt
Dynamic: author
Dynamic: author-email
Dynamic: classifier
Dynamic: description
Dynamic: description-content-type
Dynamic: home-page
Dynamic: requires-python
Dynamic: summary
